README.md
setup.cfg
setup.py
pycaesarcipher/__init__.py
pycaesarcipher/pycaesarcipher.py
pycaesarcipher/setup.py
pycaesarcipher.egg-info/PKG-INFO
pycaesarcipher.egg-info/SOURCES.txt
pycaesarcipher.egg-info/dependency_links.txt
pycaesarcipher.egg-info/entry_points.txt
pycaesarcipher.egg-info/top_level.txt